resfeci/__init__.py
resfeci/excel_split.py
resfeci-0.0.19.dist-info/LICENSE
resfeci-0.0.19.dist-info/METADATA
resfeci-0.0.19.dist-info/WHEEL
resfeci-0.0.19.dist-info/top_level.txt
resfeci-0.0.19.dist-info/RECORD
