Metadata-Version: 2.1
Name: resfeci
Version: 0.0.19
Summary: Currently allows you to quickly split an Excel report into multiple sheets or multiple reports based on unique column values.
Author-email: Jason Yearry <jasonyearry@gmail.com>
Project-URL: Homepage, https://github.com/Guitarman-Waiting-In-The-Sky/excel_splitter
Keywords: Excel,Split,opensource
Classifier: Programming Language :: Python :: 3
Classifier: License :: OSI Approved :: MIT License
Classifier: Operating System :: Microsoft :: Windows
Classifier: Development Status :: 4 - Beta
Requires-Python: >=3.7
License-File: LICENSE
